{
  "raceEthnicity": {
    "American Indian or Alaska Native": [
      "american indian",
      "alaska native",
      "alaskan native",
      "native american",
      "ai/an",
      "ai_an",
      "american indian or alaska native",
      "american indian or alaskan native",
      "american indian/alaska native",
      "american indian/alaskan native"
    ],
    "Asian": [
      "asian",
      "chinese",
      "japanese",
      "korean",
      "filipino",
      "vietnamese",
      "south asian",
      "east asian",
      "southeast asian"
    ],
    "Black or African American": [
      "black",
      "african american",
      "african-american",
      "black/aa",
      "black/african american",
      "black/african-american",
      "black or african american",
      "black or african-american",
      "african am",
      "african"
    ],
    "Hispanic or Latino": [
      "hispanic",
      "latino",
      "latina",
      "hispanic/latino",
      "hispanic or latino",
      "hispanic/latina"
    ],
    "Multiple": [
      "multiracial",
      "more than one race",
      "more than one",
      "two or more",
      "mixed",
      "multiple",
      "bi- or multi-racial",
      "multi-racial",
      "multirace"
    ],
    "Native Hawaiian or Other Pacific Islander": [
      "hawaiian",
      "pacific islander",
      "native hawaiian",
      "native hawaiian or other pacific islander",
      "native hawaiian/other pacific islander",
      "nhopi"
    ],
    "Other": ["other"],
    "Unknown/Not Reported": [
      "unknown",
      "not reported",
      "declined",
      "prefer not",
      "na",
      "n/a",
      "missing",
      "not available",
      "not applicable",
      "not collected",
      "not recorded",
      "unspecified",
      "undefined",
      "unreported",
      "not assessed",
      "no information",
      "unkown"
    ],
    "White": [
      "white",
      "caucasian",
      "european american",
      "european",
      "white or caucasian"
    ]
  },
  "sex": {
    "Female": [
      "female",
      "f",
      "woman",
      "women",
      "girl",
      "female(46,xx)",
      "female (f)"
    ],
    "Male": ["male", "m", "man", "men", "boy", "male(46,xy)"],
    "Other/Unknown": [
      "unknown",
      "not reported",
      "other",
      "prefer not to answer",
      "not applicable",
      "not available",
      "missing",
      "na",
      "n/a",
      "unk",
      "not collected",
      "unspecified",
      "undefined",
      "unreported",
      "not assessed",
      "not recorded",
      "not applicable/unknown",
      "no information",
      "refused",
      "unkown",
      "0",
      "xxy",
      "both sexes were recorded",
      "both selections were recorded"
    ]
  }
}
