[
  {
    "page": "/",
    "views": 209,
    "change": 1.6790595954073266
  },
  {
    "page": "/platforms",
    "views": 132,
    "change": -0.4509803921568628
  },
  {
    "page": "/research/studies",
    "views": 83,
    "change": null
  },
  {
    "page": "/studies",
    "views": 58,
    "change": -0.2869269949066213
  },
  {
    "page": "/about",
    "views": 16,
    "change": null
  },
  {
    "page": "/studies/phs000220",
    "views": 12,
    "change": -0.09677419354838712
  },
  {
    "page": "/studies/phs002715",
    "views": 10,
    "change": 0.20430107526881724
  },
  {
    "page": "/research/studies/phs001840",
    "views": 9,
    "change": null
  },
  {
    "page": "/data-dictionaries/ncpi-dataset-catalog",
    "views": 7,
    "change": 0.08387096774193559
  },
  {
    "page": "/example-queries",
    "views": 7,
    "change": null
  },
  {
    "page": "/studies/phs000220/variables",
    "views": 6,
    "change": null
  },
  {
    "page": "/studies/phs000964",
    "views": 5,
    "change": 3.516129032258064
  },
  {
    "page": "/studies/phs000465",
    "views": 5,
    "change": -0.3978494623655914
  },
  {
    "page": "/research/studies/phs001840/variables",
    "views": 5,
    "change": null
  },
  {
    "page": "/studies/phs000220/selected-publications",
    "views": 5,
    "change": -0.09677419354838712
  },
  {
    "page": "/status",
    "views": 4,
    "change": null
  },
  {
    "page": "/studies/phs000464/",
    "views": 4,
    "change": null
  },
  {
    "page": "/studies/phs000465/",
    "views": 4,
    "change": null
  },
  {
    "page": "/studies/phs000467",
    "views": 4,
    "change": -0.4580645161290322
  },
  {
    "page": "/research/studies/phs001228",
    "views": 4,
    "change": null
  },
  {
    "page": "/studies/phs002975",
    "views": 4,
    "change": -0.09677419354838712
  },
  {
    "page": "/studies/phs000220/",
    "views": 3,
    "change": null
  },
  {
    "page": "/studies/phs001179/",
    "views": 3,
    "change": null
  },
  {
    "page": "/studies/phs001735/",
    "views": 3,
    "change": null
  },
  {
    "page": "/studies/phs001931/",
    "views": 3,
    "change": null
  },
  {
    "page": "/studies/phs002383/",
    "views": 3,
    "change": null
  },
  {
    "page": "/studies/phs000424",
    "views": 3,
    "change": -0.09677419354838712
  },
  {
    "page": "/studies/phs001931",
    "views": 3,
    "change": -0.6989247311827957
  },
  {
    "page": "/chat",
    "views": 2,
    "change": -0.09677419354838712
  },
  {
    "page": "/studies/phs000122",
    "views": 2,
    "change": null
  },
  {
    "page": "/studies/phs000178",
    "views": 2,
    "change": null
  },
  {
    "page": "/studies/phs000178/",
    "views": 2,
    "change": 0.8064516129032258
  },
  {
    "page": "/studies/phs000285/",
    "views": 2,
    "change": null
  },
  {
    "page": "/studies/phs000289/",
    "views": 2,
    "change": null
  },
  {
    "page": "/studies/phs000439/",
    "views": 2,
    "change": null
  },
  {
    "page": "/studies/phs000466/",
    "views": 2,
    "change": null
  },
  {
    "page": "/studies/phs000467/",
    "views": 2,
    "change": null
  },
  {
    "page": "/studies/phs000470",
    "views": 2,
    "change": 0.8064516129032258
  },
  {
    "page": "/studies/phs000470/",
    "views": 2,
    "change": null
  },
  {
    "page": "/studies/phs000741/",
    "views": 2,
    "change": 0.8064516129032258
  },
  {
    "page": "/studies/phs000810",
    "views": 2,
    "change": null
  },
  {
    "page": "/studies/phs000892/",
    "views": 2,
    "change": null
  },
  {
    "page": "/studies/phs000914/",
    "views": 2,
    "change": null
  },
  {
    "page": "/studies/phs000925",
    "views": 2,
    "change": 0.8064516129032258
  },
  {
    "page": "/studies/phs001138/",
    "views": 2,
    "change": null
  },
  {
    "page": "/studies/phs001194",
    "views": 2,
    "change": null
  },
  {
    "page": "/studies/phs001217/",
    "views": 2,
    "change": 0.8064516129032258
  },
  {
    "page": "/studies/phs001222/",
    "views": 2,
    "change": null
  },
  {
    "page": "/studies/phs001287",
    "views": 2,
    "change": null
  },
  {
    "page": "/studies/phs001287/",
    "views": 2,
    "change": null
  },
  {
    "page": "/studies/phs001345",
    "views": 2,
    "change": null
  },
  {
    "page": "/studies/phs001466/",
    "views": 2,
    "change": null
  },
  {
    "page": "/studies/phs001486/",
    "views": 2,
    "change": null
  },
  {
    "page": "/studies/phs001489/",
    "views": 2,
    "change": null
  },
  {
    "page": "/studies/phs001628/",
    "views": 2,
    "change": null
  },
  {
    "page": "/studies/phs001657/",
    "views": 2,
    "change": null
  },
  {
    "page": "/studies/phs001927/",
    "views": 2,
    "change": null
  },
  {
    "page": "/studies/phs002348/",
    "views": 2,
    "change": null
  },
  {
    "page": "/studies/phs002363/",
    "views": 2,
    "change": null
  },
  {
    "page": "/studies/phs002385",
    "views": 2,
    "change": null
  },
  {
    "page": "/studies/phs002385/",
    "views": 2,
    "change": null
  },
  {
    "page": "/studies/phs002694/",
    "views": 2,
    "change": null
  },
  {
    "page": "/studies/phs003593",
    "views": 2,
    "change": null
  },
  {
    "page": "/research/studies/phs000007",
    "views": 2,
    "change": null
  },
  {
    "page": "/research/studies/phs000090",
    "views": 2,
    "change": null
  },
  {
    "page": "/research/studies/phs000925",
    "views": 2,
    "change": null
  },
  {
    "page": "/research/studies/phs000956",
    "views": 2,
    "change": null
  },
  {
    "page": "/research/studies/phs001048/variables",
    "views": 2,
    "change": null
  },
  {
    "page": "/research/studies/phs001228/selected-publications",
    "views": 2,
    "change": null
  },
  {
    "page": "/research/studies/phs001840/selected-publications",
    "views": 2,
    "change": null
  },
  {
    "page": "/studies/phs000298",
    "views": 2,
    "change": -0.09677419354838712
  },
  {
    "page": "/studies/phs000298/selected-publications",
    "views": 2,
    "change": -0.09677419354838712
  },
  {
    "page": "/studies/phs000298/variables",
    "views": 2,
    "change": null
  },
  {
    "page": "/studies/phs001179",
    "views": 2,
    "change": -0.09677419354838712
  },
  {
    "page": "/studies/phs001931/variables",
    "views": 2,
    "change": null
  },
  {
    "page": "/research/chat",
    "views": 1,
    "change": null
  },
  {
    "page": "/research/studies/phs000007/selected-publications",
    "views": 1,
    "change": null
  },
  {
    "page": "/research/studies/phs000007/variables",
    "views": 1,
    "change": null
  },
  {
    "page": "/research/studies/phs000280",
    "views": 1,
    "change": null
  },
  {
    "page": "/research/studies/phs000286",
    "views": 1,
    "change": null
  },
  {
    "page": "/research/studies/phs000462",
    "views": 1,
    "change": null
  },
  {
    "page": "/research/studies/phs000462/variables",
    "views": 1,
    "change": null
  },
  {
    "page": "/research/studies/phs000516",
    "views": 1,
    "change": null
  },
  {
    "page": "/research/studies/phs000571",
    "views": 1,
    "change": null
  },
  {
    "page": "/research/studies/phs000571/selected-publications",
    "views": 1,
    "change": null
  },
  {
    "page": "/research/studies/phs000667",
    "views": 1,
    "change": null
  },
  {
    "page": "/research/studies/phs000667/variables",
    "views": 1,
    "change": null
  },
  {
    "page": "/research/studies/phs000925/variables",
    "views": 1,
    "change": null
  },
  {
    "page": "/research/studies/phs000956/variables",
    "views": 1,
    "change": null
  },
  {
    "page": "/research/studies/phs001048",
    "views": 1,
    "change": null
  },
  {
    "page": "/research/studies/phs001999",
    "views": 1,
    "change": null
  },
  {
    "page": "/research/studies/phs003002",
    "views": 1,
    "change": null
  },
  {
    "page": "/research/studies/phs003600",
    "views": 1,
    "change": null
  },
  {
    "page": "/research/studies/phs003887",
    "views": 1,
    "change": null
  },
  {
    "page": "/research/studies/phs003887/selected-publications",
    "views": 1,
    "change": null
  },
  {
    "page": "/research/studies/phs003887/variables",
    "views": 1,
    "change": null
  },
  {
    "page": "/studies/phs000001",
    "views": 1,
    "change": null
  },
  {
    "page": "/studies/phs000006",
    "views": 1,
    "change": null
  },
  {
    "page": "/studies/phs000007",
    "views": 1,
    "change": -0.09677419354838712
  },
  {
    "page": "/studies/phs000007/",
    "views": 1,
    "change": null
  },
  {
    "page": "/studies/phs000016",
    "views": 1,
    "change": null
  },
  {
    "page": "/studies/phs000017",
    "views": 1,
    "change": null
  },
  {
    "page": "/studies/phs000018",
    "views": 1,
    "change": null
  },
  {
    "page": "/studies/phs000019",
    "views": 1,
    "change": null
  },
  {
    "page": "/studies/phs000020",
    "views": 1,
    "change": null
  },
  {
    "page": "/studies/phs000021",
    "views": 1,
    "change": null
  },
  {
    "page": "/studies/phs000086",
    "views": 1,
    "change": null
  },
  {
    "page": "/studies/phs000088",
    "views": 1,
    "change": null
  },
  {
    "page": "/studies/phs000089",
    "views": 1,
    "change": null
  },
  {
    "page": "/studies/phs000090",
    "views": 1,
    "change": null
  },
  {
    "page": "/studies/phs000091",
    "views": 1,
    "change": null
  },
  {
    "page": "/studies/phs000092",
    "views": 1,
    "change": null
  },
  {
    "page": "/studies/phs000093",
    "views": 1,
    "change": null
  },
  {
    "page": "/studies/phs000094",
    "views": 1,
    "change": null
  },
  {
    "page": "/studies/phs000095",
    "views": 1,
    "change": null
  },
  {
    "page": "/studies/phs000096",
    "views": 1,
    "change": null
  },
  {
    "page": "/studies/phs000100",
    "views": 1,
    "change": null
  },
  {
    "page": "/studies/phs000101",
    "views": 1,
    "change": null
  },
  {
    "page": "/studies/phs000102",
    "views": 1,
    "change": null
  },
  {
    "page": "/studies/phs000103",
    "views": 1,
    "change": null
  },
  {
    "page": "/studies/phs000125",
    "views": 1,
    "change": null
  },
  {
    "page": "/studies/phs000126",
    "views": 1,
    "change": null
  },
  {
    "page": "/studies/phs000127",
    "views": 1,
    "change": null
  },
  {
    "page": "/studies/phs000128",
    "views": 1,
    "change": null
  },
  {
    "page": "/studies/phs000139",
    "views": 1,
    "change": null
  },
  {
    "page": "/studies/phs000274",
    "views": 1,
    "change": null
  },
  {
    "page": "/studies/phs000424/",
    "views": 1,
    "change": null
  },
  {
    "page": "/studies/phs000424/selected-publications",
    "views": 1,
    "change": null
  },
  {
    "page": "/studies/phs000424/variables",
    "views": 1,
    "change": null
  },
  {
    "page": "/studies/phs000464",
    "views": 1,
    "change": null
  },
  {
    "page": "/studies/phs000530",
    "views": 1,
    "change": null
  },
  {
    "page": "/studies/phs000711",
    "views": 1,
    "change": null
  },
  {
    "page": "/studies/phs000748",
    "views": 1,
    "change": -0.09677419354838712
  },
  {
    "page": "/studies/phs000820/",
    "views": 1,
    "change": null
  },
  {
    "page": "/studies/phs000925/",
    "views": 1,
    "change": null
  },
  {
    "page": "/studies/phs000925/variables",
    "views": 1,
    "change": null
  },
  {
    "page": "/studies/phs000956/",
    "views": 1,
    "change": null
  },
  {
    "page": "/studies/phs000971",
    "views": 1,
    "change": -0.09677419354838712
  },
  {
    "page": "/studies/phs000971/selected-publications",
    "views": 1,
    "change": -0.09677419354838712
  },
  {
    "page": "/studies/phs000971/variables",
    "views": 1,
    "change": null
  },
  {
    "page": "/studies/phs001179/selected-publications",
    "views": 1,
    "change": null
  },
  {
    "page": "/studies/phs001217",
    "views": 1,
    "change": null
  },
  {
    "page": "/studies/phs001218",
    "views": 1,
    "change": -0.6989247311827957
  },
  {
    "page": "/studies/phs001247/",
    "views": 1,
    "change": null
  },
  {
    "page": "/studies/phs001398/",
    "views": 1,
    "change": null
  },
  {
    "page": "/studies/phs001416/",
    "views": 1,
    "change": null
  },
  {
    "page": "/studies/phs001420/",
    "views": 1,
    "change": null
  },
  {
    "page": "/studies/phs001486",
    "views": 1,
    "change": null
  },
  {
    "page": "/studies/phs001598/",
    "views": 1,
    "change": null
  },
  {
    "page": "/studies/phs001605",
    "views": 1,
    "change": null
  },
  {
    "page": "/studies/phs001607",
    "views": 1,
    "change": -0.09677419354838712
  },
  {
    "page": "/studies/phs001683/",
    "views": 1,
    "change": null
  },
  {
    "page": "/studies/phs001714/",
    "views": 1,
    "change": -0.09677419354838712
  },
  {
    "page": "/studies/phs001727",
    "views": 1,
    "change": -0.09677419354838712
  },
  {
    "page": "/studies/phs001948",
    "views": 1,
    "change": null
  },
  {
    "page": "/studies/phs002808",
    "views": 1,
    "change": -0.7741935483870968
  },
  {
    "page": "/studies/phs003045",
    "views": 1,
    "change": null
  },
  {
    "page": "/studies/phs003529",
    "views": 1,
    "change": null
  },
  {
    "page": "/studies/phs003783",
    "views": 1,
    "change": -0.5483870967741935
  },
  {
    "page": "/platforms)",
    "views": 0,
    "change": -1.0
  },
  {
    "page": "/studies/phs000179",
    "views": 0,
    "change": -1.0
  },
  {
    "page": "/studies/phs000200",
    "views": 0,
    "change": -1.0
  },
  {
    "page": "/studies/phs000209",
    "views": 0,
    "change": -1.0
  },
  {
    "page": "/studies/phs000209/selected-publications",
    "views": 0,
    "change": -1.0
  },
  {
    "page": "/studies/phs000287",
    "views": 0,
    "change": -1.0
  },
  {
    "page": "/studies/phs000468",
    "views": 0,
    "change": -1.0
  },
  {
    "page": "/studies/phs000471",
    "views": 0,
    "change": -1.0
  },
  {
    "page": "/studies/phs000869",
    "views": 0,
    "change": -1.0
  },
  {
    "page": "/studies/phs000892",
    "views": 0,
    "change": -1.0
  },
  {
    "page": "/studies/phs000921",
    "views": 0,
    "change": -1.0
  },
  {
    "page": "/studies/phs000951",
    "views": 0,
    "change": -1.0
  },
  {
    "page": "/studies/phs000997",
    "views": 0,
    "change": -1.0
  },
  {
    "page": "/studies/phs000997/selected-publications",
    "views": 0,
    "change": -1.0
  },
  {
    "page": "/studies/phs001110",
    "views": 0,
    "change": -1.0
  },
  {
    "page": "/studies/phs001175",
    "views": 0,
    "change": -1.0
  },
  {
    "page": "/studies/phs001416",
    "views": 0,
    "change": -1.0
  },
  {
    "page": "/studies/phs001420",
    "views": 0,
    "change": -1.0
  },
  {
    "page": "/studies/phs001489",
    "views": 0,
    "change": -1.0
  },
  {
    "page": "/studies/phs001539",
    "views": 0,
    "change": -1.0
  },
  {
    "page": "/studies/phs001543",
    "views": 0,
    "change": -1.0
  },
  {
    "page": "/studies/phs001545",
    "views": 0,
    "change": -1.0
  },
  {
    "page": "/studies/phs001546",
    "views": 0,
    "change": -1.0
  },
  {
    "page": "/studies/phs001579",
    "views": 0,
    "change": -1.0
  },
  {
    "page": "/studies/phs001598",
    "views": 0,
    "change": -1.0
  },
  {
    "page": "/studies/phs001608",
    "views": 0,
    "change": -1.0
  },
  {
    "page": "/studies/phs001611",
    "views": 0,
    "change": -1.0
  },
  {
    "page": "/studies/phs001612",
    "views": 0,
    "change": -1.0
  },
  {
    "page": "/studies/phs001644",
    "views": 0,
    "change": -1.0
  },
  {
    "page": "/studies/phs001657",
    "views": 0,
    "change": -1.0
  },
  {
    "page": "/studies/phs001662",
    "views": 0,
    "change": -1.0
  },
  {
    "page": "/studies/phs001682",
    "views": 0,
    "change": -1.0
  },
  {
    "page": "/studies/phs001735",
    "views": 0,
    "change": -1.0
  },
  {
    "page": "/studies/phs001913",
    "views": 0,
    "change": -1.0
  },
  {
    "page": "/studies/phs001963",
    "views": 0,
    "change": -1.0
  },
  {
    "page": "/studies/phs002183",
    "views": 0,
    "change": -1.0
  },
  {
    "page": "/studies/phs002183/selected-publications",
    "views": 0,
    "change": -1.0
  },
  {
    "page": "/studies/phs003046",
    "views": 0,
    "change": -1.0
  },
  {
    "page": "/studies/phs003543",
    "views": 0,
    "change": -1.0
  }
]